[
    {
        "city": "london"
    },
    {
        "city": "san francisco"
    },
    {
        "city": "new york"
    },
    {
        "city": "paris"
    },
    {
        "city": "los angeles"
    },
    {
        "city": "tokyo"
    },
    {
        "city": "seattle"
    },
    {
        "city": "vancouver"
    },
    {
        "city": "chicago"
    },
    {
        "city": "seoul"
    },
    {
        "city": "hanoi"
    },
    {
        "city": "rome"
    },    
    {
        "city": "barcelona"
    },
    {
        "city": "honolulu"
    },
    {
        "city": "san diego"
    },
    {
        "city": "las vegas"
    },
    {
        "city": "atlanta"
    },
    {
        "city": "sydney"
    },
    {
        "city": "boston"
    },
    {
        "city": "washington dc"
    },
    {
        "city": "miami"
    },
    {
        "city": "mexico city"
    },
    {
        "city": "phoenix"
    },
    {
        "city": "dallas"
    },
    {
        "city": "madrid"
    },
    {
        "city": "berlin"
    }
]